arrp_dataset/__init__.py
arrp_dataset/__version__.py
arrp_dataset/build.py
arrp_dataset/load.py
arrp_dataset/utils/__init__.py
arrp_dataset/utils/download_genome.py
arrp_dataset/utils/downloader.py
arrp_dataset/utils/expand_regions.py
arrp_dataset/utils/get_cell_lines.py
arrp_dataset/utils/one_hot_encode_expanded_regions.py
arrp_dataset/utils/one_hot_encode_regions.py
arrp_dataset/utils/ungzip.py
arrp_dataset/utils/ungzip_data.py
arrp_dataset-1.0.2.dist-info/LICENSE
arrp_dataset-1.0.2.dist-info/METADATA
arrp_dataset-1.0.2.dist-info/WHEEL
arrp_dataset-1.0.2.dist-info/top_level.txt
arrp_dataset-1.0.2.dist-info/RECORD
