Metadata-Version: 2.1
Name: arrp-dataset
Version: 1.0.2
Summary: Simple python tool to create dataset for arrps.
Home-page: https://github.com/LucaCappelletti94/cnn-code
Author: Luca Cappelletti
Author-email: cappelletti.luca94@gmail.com
License: MIT
Platform: UNKNOWN
Classifier: Development Status :: 3 - Alpha
Classifier: License :: OSI Approved :: MIT License
Classifier: Programming Language :: Python :: 3
Requires-Dist: tqdm
Requires-Dist: typing
Requires-Dist: pandas
Requires-Dist: sklearn
Requires-Dist: fasta-one-hot-encoder
Provides-Extra: test
Requires-Dist: pytest ; extra == 'test'
Requires-Dist: pytest-cov ; extra == 'test'
Requires-Dist: coveralls ; extra == 'test'
